odoo/addons/product_multi_barcode_stock_menu/README.rst
odoo/addons/product_multi_barcode_stock_menu/__init__.py
odoo/addons/product_multi_barcode_stock_menu/__manifest__.py
odoo/addons/product_multi_barcode_stock_menu/i18n/it.po
odoo/addons/product_multi_barcode_stock_menu/i18n/product_multi_barcode_stock_menu.pot
odoo/addons/product_multi_barcode_stock_menu/readme/CONTRIBUTORS.rst
odoo/addons/product_multi_barcode_stock_menu/readme/CREDITS.rst
odoo/addons/product_multi_barcode_stock_menu/readme/DESCRIPTION.rst
odoo/addons/product_multi_barcode_stock_menu/readme/USAGE.rst
odoo/addons/product_multi_barcode_stock_menu/static/description/icon.png
odoo/addons/product_multi_barcode_stock_menu/static/description/index.html
odoo/addons/product_multi_barcode_stock_menu/views/barcode_view.xml
odoo_addon_product_multi_barcode_stock_menu-16.0.1.0.0.3.dist-info/METADATA
odoo_addon_product_multi_barcode_stock_menu-16.0.1.0.0.3.dist-info/WHEEL
odoo_addon_product_multi_barcode_stock_menu-16.0.1.0.0.3.dist-info/top_level.txt
odoo_addon_product_multi_barcode_stock_menu-16.0.1.0.0.3.dist-info/RECORD
