Metadata-Version: 2.1
Name: odoo-addon-product-multi-barcode-stock-menu
Version: 16.0.1.0.0.3
Summary: Multiple barcodes menu
Home-page: https://github.com/OCA/stock-logistics-barcode
Author: Ilyas, Ooops404, Odoo Community Association (OCA)
Author-email: support@odoo-community.org
License: AGPL-3
Platform: UNKNOWN
Classifier: Programming Language :: Python
Classifier: Framework :: Odoo
Classifier: Framework :: Odoo :: 16.0
Classifier: License :: OSI Approved :: GNU Affero General Public License v3
Requires-Python: >=3.10
Requires-Dist: odoo-addon-product-multi-barcode <16.1dev,>=16.0dev
Requires-Dist: odoo <16.1dev,>=16.0a
